hxm/__init__.py
hxm-0.1.0.dist-info/LICENSE
hxm-0.1.0.dist-info/METADATA
hxm-0.1.0.dist-info/WHEEL
hxm-0.1.0.dist-info/RECORD
